Metadata-Version: 1.1
Name: medicalsegment
Version: 0.1.0
Summary: Medical imaging segmentation
Home-page: https://github.com/yngtodd/segment
Author: Todd Young
Author-email: youngmt1@ornl.gov
License: MIT
Keywords: segment
Platform: UNKNOWN
Classifier: Development Status :: 2 - Pre-Alpha
Classifier: Intended Audience :: Developers
Classifier: License :: OSI Approved :: MIT License
Classifier: Natural Language :: English
Classifier: Programming Language :: Python :: 3.6
Classifier: Programming Language :: Python :: Implementation :: PyPy
